qrw_circuit/CTQW.py
qrw_circuit/__init__.py
qrw_circuit-0.1.dist-info/METADATA
qrw_circuit-0.1.dist-info/WHEEL
qrw_circuit-0.1.dist-info/top_level.txt
qrw_circuit-0.1.dist-info/RECORD
